redditreader/__init__.py
redditreader/redditreader.py
Redreader-0.1.3.dist-info/METADATA
Redreader-0.1.3.dist-info/WHEEL
Redreader-0.1.3.dist-info/top_level.txt
Redreader-0.1.3.dist-info/RECORD
