Metadata-Version: 2.1
Name: Redreader
Version: 0.1.3
Summary: RedditReader - Let your stories come to life
Author: Aghastmuffin
Author-email: helpredditreader@gmail.com
Keywords: python,video,stream,RedditReader,Read Reddit,Stories,automated readreddit
Classifier: Development Status :: 5 - Production/Stable
Classifier: Intended Audience :: Developers
Classifier: Programming Language :: Python :: 3
Classifier: Operating System :: Unix
Classifier: Operating System :: MacOS :: MacOS X
Classifier: Operating System :: Microsoft :: Windows
Requires-Dist: PyQt6
Requires-Dist: moviepy
Requires-Dist: vosk
Requires-Dist: pyttsx3
Requires-Dist: yt-dlp
